mira_sdk/__init__.py
mira_sdk/client.py
mira_sdk/exceptions/__init__.py
mira_sdk/mira/__init__.py
mira_sdk/mira/compound_flow.py
mira_sdk/mira/constants.py
mira_sdk/mira/exceptions.py
mira_sdk/mira/flow.py
mira_sdk/mira/client/__init__.py
mira_sdk/mira/client/async_console.py
mira_sdk/mira/client/async_mira_client.py
mira_sdk/mira/client/console.py
mira_sdk/mira/client/mira_client.py
mira_sdk/mira/integrations/__init__.py
mira_sdk/mira/integrations/composio.py
mira_sdk/mira/models/__init__.py
mira_sdk/mira/models/input.py
mira_sdk/mira/models/metadata.py
mira_sdk/mira/models/model.py
mira_sdk/mira/utils/__init__.py
mira_sdk/mira/utils/util.py
mira_sdk/mira/utils/validation.py
mira_sdk/mira/utils/yaml.py
tests/__init__.py
tests/test_async.py
tests/test_new.py
mira_sdk-0.1.15.dist-info/METADATA
mira_sdk-0.1.15.dist-info/WHEEL
mira_sdk-0.1.15.dist-info/top_level.txt
mira_sdk-0.1.15.dist-info/RECORD
