Metadata-Version: 2.2
Name: mira_sdk
Version: 0.1.15
Summary: A Python SDK for the Mira API
Home-page: https://github.com/Aroha-Labs/mira-sdk-python
Author-email: sarim2000 <sarimbleedblue@gmail.com>
License: MIT
Requires-Python: >=3.10
Requires-Dist: pyyaml>=6.0.2
Requires-Dist: requests>=2.32.3
Requires-Dist: semantic-version>=2.10.0
Requires-Dist: aiohttp>=3.10.10
Requires-Dist: pytest-asyncio>=0.24.0
Requires-Dist: pydantic>=2.10.4
Dynamic: home-page
Dynamic: requires-python
